pysplitcue/__init__.py
pysplitcue/datastrings.py
pysplitcue/exceptions.py
pysplitcue/main.py
pysplitcue/splitcue.py
pysplitcue/str_utils.py
pysplitcue-2.1.5.data/data/share/man/man1/pysplitcue.1.gz
pysplitcue-2.1.5.data/data/share/pysplitcue/AUTHORS
pysplitcue-2.1.5.data/data/share/pysplitcue/BUGS
pysplitcue-2.1.5.data/data/share/pysplitcue/CHANGELOG
pysplitcue-2.1.5.data/data/share/pysplitcue/COPYING
pysplitcue-2.1.5.data/data/share/pysplitcue/README.md
pysplitcue-2.1.5.data/data/share/pysplitcue/TODO
pysplitcue-2.1.5.dist-info/AUTHORS
pysplitcue-2.1.5.dist-info/COPYING
pysplitcue-2.1.5.dist-info/METADATA
pysplitcue-2.1.5.dist-info/WHEEL
pysplitcue-2.1.5.dist-info/entry_points.txt
pysplitcue-2.1.5.dist-info/top_level.txt
pysplitcue-2.1.5.dist-info/RECORD
