Metadata-Version: 2.1
Name: pysplitcue
Version: 2.1.5
Summary: CUE sheet Splitter, based on shntool and cuetools libraries.
Home-page: https://github.com/jeanslack/pysplitcue
Author: Gianluca Pernigotto - Jeanslack
Author-email: <jeanlucperni@gmail.com>
License: Type 'pysplitcue -h' for help or, more detailed, run 'man pysplitcue'
Platform: Linux
Platform: Unix
Platform: MacOS
Classifier: Development Status :: 4 - Beta
Classifier: Environment :: Console
Classifier: Intended Audience :: End Users/Desktop
Classifier: License :: OSI Approved :: GNU General Public License v3 (GPLv3)
Classifier: Natural Language :: English
Classifier: Operating System :: MacOS :: MacOS X
Classifier: Operating System :: POSIX :: Linux
Classifier: Programming Language :: Python :: 3
Classifier: Programming Language :: Python :: 3.6
Classifier: Programming Language :: Python :: 3.7
Classifier: Programming Language :: Python :: 3.8
Classifier: Programming Language :: Python :: 3.9
Classifier: Topic :: Multimedia :: Sound/Audio :: Conversion
Classifier: Topic :: Utilities
Requires-Python: >=3.6
License-File: COPYING
License-File: AUTHORS
Requires-Dist: chardet (>=4.0.0)
